{"_type":"export","__export_format":4,"__export_date":"2022-02-18T20:06:23.629Z","__export_source":"insomnia.desktop.app:v2021.7.2","resources":[{"_id":"req_75c8a4907db649a09c71f3fc1ae0e742","parentId":"fld_1915944785fd46949391c09774160743","modified":1645214420620,"created":1633567740590,"url":"{{ _.base_url }}/repositories","name":"Create","description":"","method":"POST","body":{"mimeType":"application/json","text":"{\n\t\"title\": \"unform\",\n\t\"url\": \"https://github.com/unform/unform\",\n\t\"techs\":  [\n\t\t\"react\", \"react-native\", \"form\"\n\t]\n}"},"parameters":[],"headers":[{"name":"Content-Type","value":"application/json","id":"pair_6caf1f5ceaf146238b86686f4d5a9174"}],"authentication":{},"metaSortKey":-1632254918908.25,"isPrivate":false,"settingStoreCookies":true,"settingSendCookies":true,"settingDisableRenderRequestBody":false,"settingEncodeUrl":true,"settingRebuildPath":true,"settingFollowRedirects":"global","_type":"request"},{"_id":"fld_1915944785fd46949391c09774160743","parentId":"wrk_2276638d425043cea444bbfefd570148","modified":1645213509082,"created":1633567735369,"name":"Repositories","description":"","environment":{},"environmentPropertyOrder":null,"metaSortKey":-1632911291612.25,"_type":"request_group"},{"_id":"wrk_2276638d425043cea444bbfefd570148","parentId":null,"modified":1645213456392,"created":1632254583171,"name":"Ignite - Desafio: Corrigindo o código","description":"","scope":"collection","_type":"workspace"},{"_id":"req_2d4011c3afe6462fb7aa3f135d8ad3cf","parentId":"fld_1915944785fd46949391c09774160743","modified":1645213580054,"created":1633567863032,"url":"{{ _.base_url }}/repositories","name":"List","description":"","method":"GET","body":{},"parameters":[],"headers":[],"authentication":{},"metaSortKey":-1632254910185.875,"isPrivate":false,"settingStoreCookies":true,"settingSendCookies":true,"settingDisableRenderRequestBody":false,"settingEncodeUrl":true,"settingRebuildPath":true,"settingFollowRedirects":"global","_type":"request"},{"_id":"req_7991d48e948f41ef907d437f876f978d","parentId":"fld_1915944785fd46949391c09774160743","modified":1645214674065,"created":1633567914634,"url":"{{ _.base_url }}/repositories/f760382a-588f-40b2-809f-a301891ac10a","name":"Update","description":"","method":"PUT","body":{"mimeType":"application/json","text":"{\n\t\"title\": \"unform\",\n\t\"url\": \"https://github.com/unform/unform\",\n\t\"techs\":  [\n\t\t\"react\", \"react-native\", \"form\"\n\t]\n}"},"parameters":[],"headers":[{"name":"Content-Type","value":"application/json","id":"pair_6caf1f5ceaf146238b86686f4d5a9174"}],"authentication":{},"metaSortKey":-1632254905824.6875,"isPrivate":false,"settingStoreCookies":true,"settingSendCookies":true,"settingDisableRenderRequestBody":false,"settingEncodeUrl":true,"settingRebuildPath":true,"settingFollowRedirects":"global","_type":"request"},{"_id":"req_90f9a40a41a94ee5a1b8d3351b712e77","parentId":"fld_1915944785fd46949391c09774160743","modified":1645214372601,"created":1633568563016,"url":"{{ _.base_url }}/repositories/f760382a-588f-40b2-809f-a301891ac10a","name":"Delete","description":"","method":"DELETE","body":{},"parameters":[],"headers":[{"id":"pair_d9b6849e39814a0bb7ddf63b9e7e7b00","name":"username","value":"eliasmcastro","description":""}],"authentication":{},"metaSortKey":-1632254903644.0938,"isPrivate":false,"settingStoreCookies":true,"settingSendCookies":true,"settingDisableRenderRequestBody":false,"settingEncodeUrl":true,"settingRebuildPath":true,"settingFollowRedirects":"global","_type":"request"},{"_id":"req_82d46e76125f47488c2a422af3ae2e42","parentId":"fld_1915944785fd46949391c09774160743","modified":1645214428564,"created":1633568589881,"url":"{{ _.base_url }}/repositories/26f25971-3ff3-4b3c-8a78-7a0895aea856/like","name":"Like","description":"","method":"POST","body":{},"parameters":[],"headers":[{"id":"pair_d9b6849e39814a0bb7ddf63b9e7e7b00","name":"username","value":"eliasmcastro","description":""}],"authentication":{},"metaSortKey":-1632254902553.7969,"isPrivate":false,"settingStoreCookies":true,"settingSendCookies":true,"settingDisableRenderRequestBody":false,"settingEncodeUrl":true,"settingRebuildPath":true,"settingFollowRedirects":"global","_type":"request"},{"_id":"env_79e07998ca112ca98fec7c718acf470078eaaaec","parentId":"wrk_2276638d425043cea444bbfefd570148","modified":1645213464586,"created":1632254583240,"name":"Base Environment","data":{"base_url":"http://localhost:3333"},"dataPropertyOrder":{"&":["base_url"]},"color":null,"isPrivate":false,"metaSortKey":1632254583240,"_type":"environment"},{"_id":"jar_79e07998ca112ca98fec7c718acf470078eaaaec","parentId":"wrk_2276638d425043cea444bbfefd570148","modified":1632254583242,"created":1632254583242,"name":"Default Jar","cookies":[],"_type":"cookie_jar"},{"_id":"spc_6d1126fd41e54ef0914705fc5f4b86fb","parentId":"wrk_2276638d425043cea444bbfefd570148","modified":1632254583184,"created":1632254583184,"fileName":"Ignite - Primeiro projeto com Node.js","contents":"","contentType":"yaml","_type":"api_spec"}]}